dbprocessing/DBfile.py
dbprocessing/DBlogging.py
dbprocessing/DBqueue.py
dbprocessing/DBstrings.py
dbprocessing/DButils.py
dbprocessing/Diskfile.py
dbprocessing/Utils.py
dbprocessing/Version.py
dbprocessing/__init__.py
dbprocessing/dbprocessing.py
dbprocessing/inspector.py
dbprocessing/module.py
dbprocessing/reports.py
dbprocessing/runMe.py
dbprocessing/tables.py
dbprocessing/__pycache__/DBfile.cpython-39.pyc
dbprocessing/__pycache__/DBlogging.cpython-39.pyc
dbprocessing/__pycache__/DBqueue.cpython-39.pyc
dbprocessing/__pycache__/DBstrings.cpython-39.pyc
dbprocessing/__pycache__/DButils.cpython-39.pyc
dbprocessing/__pycache__/Diskfile.cpython-39.pyc
dbprocessing/__pycache__/Utils.cpython-39.pyc
dbprocessing/__pycache__/Version.cpython-39.pyc
dbprocessing/__pycache__/__init__.cpython-39.pyc
dbprocessing/__pycache__/dbprocessing.cpython-39.pyc
dbprocessing/__pycache__/inspector.cpython-39.pyc
dbprocessing/__pycache__/module.cpython-39.pyc
dbprocessing/__pycache__/reports.cpython-39.pyc
dbprocessing/__pycache__/runMe.cpython-39.pyc
dbprocessing/__pycache__/tables.cpython-39.pyc
dbprocessing-0.1.0.data/scripts/CreateDB.py
dbprocessing-0.1.0.data/scripts/DBRunner.py
dbprocessing-0.1.0.data/scripts/MigrateDB.py
dbprocessing-0.1.0.data/scripts/ProcessQueue.py
dbprocessing-0.1.0.data/scripts/addFromConfig.py
dbprocessing-0.1.0.data/scripts/addProductProcessLink.py
dbprocessing-0.1.0.data/scripts/changeProductDir.py
dbprocessing-0.1.0.data/scripts/clearProcessingFlag.py
dbprocessing-0.1.0.data/scripts/compareDB.py
dbprocessing-0.1.0.data/scripts/configFromDB.py
dbprocessing-0.1.0.data/scripts/coveragePlot.py
dbprocessing-0.1.0.data/scripts/dbOnlyFiles.py
dbprocessing-0.1.0.data/scripts/deleteAllDBFiles.py
dbprocessing-0.1.0.data/scripts/fast_data.py
dbprocessing-0.1.0.data/scripts/flushProcessQueue.py
dbprocessing-0.1.0.data/scripts/histogramCodes.py
dbprocessing-0.1.0.data/scripts/htmlCoverage.py
dbprocessing-0.1.0.data/scripts/linkUningested.py
dbprocessing-0.1.0.dist-info/METADATA
dbprocessing-0.1.0.dist-info/WHEEL
dbprocessing-0.1.0.dist-info/top_level.txt
dbprocessing-0.1.0.dist-info/RECORD
